{"type": "Feature", "id": 12512440, "properties": {"woe:id": 12512440, "woe:parent_id": 59182, "woe:name": "Quepos Managua Airport", "woe:placetype": 14, "woe:placetype_name": "Airport", "woe:lang": "ENG", "iso:country": "CR", "meta:provider": ["geoplanet:7.3.1", "geoplanet:7.3.2", "geoplanet:7.4.0", "geoplanet:7.4.1", "geoplanet:7.5.1", "geoplanet:7.5.2", "geoplanet:7.6.0", "geoplanet:7.8.1", "geoplanet:7.9.0", "geoplanet:7.10.0", "geoplanet:8.0.0", "woeplanet:8.0.0"], "meta:indexed": "2020-08-20T20:48:42.471891", "woe:alias_ENG_V": ["XQP Airport", "XQP"], "meta:updated": "2020-08-22T01:56:32.666787", "woe:hierarchy": {"continent": 24865672, "country": 23424791, "town": 0, "planet": 1, "county": 26808785, "suburb": 0, "state": 2345087, "region": 0, "localadmin": 26809132}, "woe:timezone_id": 28350748, "woe:hash": "d1sjtx387nqp", "woe:centroid": [-84.131104, 9.4442], "geom:latitude": 9.4442, "geom:longitude": -84.131104, "geom:hash": "d1sjtx387nqp", "woe:latitude": 9.4442, "geom:centroid": [-84.131104, 9.4442], "woe:longitude": -84.131104, "woe:repo": "woeplanet-airport-cr"}, "geometry": {"coordinates": [-84.131104, 9.4442], "type": "Point"}}