{"type": "Feature", "id": 12524317, "properties": {"woe:id": 12524317, "woe:parent_id": 59142, "woe:name": "Puerto Jimenez Airport", "woe:placetype": 14, "woe:placetype_name": "Airport", "woe:lang": "ENG", "iso:country": "CR", "meta:provider": ["geoplanet:7.3.1", "geoplanet:7.3.2", "geoplanet:7.4.0", "geoplanet:7.4.1", "geoplanet:7.5.1", "geoplanet:7.5.2", "geoplanet:7.6.0", "geoplanet:7.8.1", "geoplanet:7.9.0", "geoplanet:7.10.0", "geoplanet:8.0.0", "woeplanet:8.0.0"], "meta:indexed": "2020-08-20T20:48:42.481318", "woe:alias_ENG_V": ["PJM Airport", "PJM", "Pto Jimenez Airport"], "meta:updated": "2020-08-22T01:56:32.670461", "woe:hierarchy": {"continent": 24865672, "country": 23424791, "town": 0, "planet": 1, "county": 26808810, "suburb": 0, "state": 2345087, "region": 0, "localadmin": 26809124}, "woe:timezone_id": 28350748, "woe:hash": "d1s8xfwkb0jy", "woe:centroid": [-83.322708, 8.53994], "geom:latitude": 8.53994, "geom:longitude": -83.322708, "geom:hash": "d1s8xfwkb0jy", "woe:latitude": 8.53994, "geom:centroid": [-83.322708, 8.53994], "woe:longitude": -83.322708, "woe:repo": "woeplanet-airport-cr"}, "geometry": {"coordinates": [-83.322708, 8.53994], "type": "Point"}}